metachange.py
editpdf-0.1.0.dist-info/LICENSE.md
editpdf-0.1.0.dist-info/METADATA
editpdf-0.1.0.dist-info/WHEEL
editpdf-0.1.0.dist-info/entry_points.txt
editpdf-0.1.0.dist-info/top_level.txt
editpdf-0.1.0.dist-info/RECORD
