Metadata-Version: 2.1
Name: editpdf
Version: 0.1.0
Summary: PDF File title editing CLI application
Home-page: https://github.com/kar-re/pdftitle
Author: Kaspian Jakobsson
Author-email: kaspian.jakobsson@gmail.com
License: MIT
Platform: UNKNOWN
Classifier: Programming Language :: Python :: 3
Classifier: License :: OSI Approved :: MIT License
Classifier: Operating System :: OS Independent
Requires-Python: >=3.6
Requires-Dist: Click
Requires-Dist: pdfrw
